kypo/topology_definition/__init__.py
kypo/topology_definition/image_naming.py
kypo/topology_definition/models.py
kypo/topology_definition/utils.py
kypo/topology_definition/validators.py
topology_definition-0.5.10.dist-info/LICENSE
topology_definition-0.5.10.dist-info/METADATA
topology_definition-0.5.10.dist-info/WHEEL
topology_definition-0.5.10.dist-info/top_level.txt
topology_definition-0.5.10.dist-info/RECORD
