Metadata-Version: 2.1
Name: topology-definition
Version: 0.5.10
Summary: topology-definition
Home-page: UNKNOWN
Author: cyberrangecz
License: UNKNOWN
Platform: UNKNOWN
Requires-Python: >=3
Requires-Dist: yamlize>=0.6
Requires-Dist: structlog>=19.2
Requires-Dist: netaddr>=0.7
